src/ALU.v
module ALU(
    input [31:0] X,
    input [31:0] Y,
    input [3:0] OP,

    output reg [31:0] RESULT,
    output isEqual
);

    wire signed [31:0] X_signed = X;
    wire signed [31:0] Y_signed = Y;

    assign isEqual = X == Y;

    always @(*) begin
        case (OP)
            0: RESULT <= X + Y; // add
            1: RESULT <= X - Y; // sub
            2: RESULT <= X & Y; // and
            3: RESULT <= X | Y; // or
            4: RESULT <= X ^ Y; // xor
            5: RESULT <= X << Y; // shift left logical
            6: RESULT <= X >> Y; // shift right logical
            7: RESULT <= X_signed >>> Y; // shift right arithmetic
            8: RESULT <= (X_signed < Y_signed ? 1 : 0); // set less than (slt)
            9: RESULT <= (X < Y ? 1 : 0); // set less than (sltu)
        endcase
    end

endmodule

testbench/tb_ALU.v
`include "ALU.v"
`timescale 1ns / 100ps 

module tb_ALU;
    reg [31:0] a;
    reg [31:0] b;
    reg [3:0]  op;

    wire [31:0] result;
    wire isEqual;

    ALU alu(a, b, op, result, isEqual);

    initial begin
        #20;
        
        // add
        a = 5;          b = 5;      op = 0; #20;
        // sub
        a = 66;         b = 11;     op = 1; #20;        
        // and
        a = 3'b101;     b = 3'b110; op = 2; #20;
        // or
        a = 3'b101;     b = 3'b110; op = 3; #20;
        // xor
        a = 3'b110;     b = 3'b010; op = 4; #20;
        // sll (Shift Left Logical)
        a = 1;          b = 3;      op = 5; #20;
        // srl (Shift Right Logical)
        a = 8;          b = 2;      op = 6; #20;
        // sra (Shift Right Arithmetic)
        a = -8;         b = 2;      op = 7; #20;
        // slt (Set Less Than)
        a = -1;         b = 9;      op = 8; #20;
        // sltu (Set Less Than Unsigned)
        a = -1;         b = 9;      op = 9; #20;
    end

    initial begin
        $dumpfile("vcd/alu.vcd");
        $dumpvars(0, tb_ALU);
    end
endmodule

testbench/vcd/alu.vcd
$date
	Sun Dec  4 14:45:25 2022
$end
$version
	Icarus Verilog
$end
$timescale
	100ps
$end
$scope module tb_ALU $end
$var wire 32 ! result [31:0] $end
$var wire 1 " isEqual $end
$var reg 32 # a [31:0] $end
$var reg 32 $ b [31:0] $end
$var reg 4 % op [3:0] $end
$scope module alu $end
$var wire 4 & OP [3:0] $end
$var wire 32 ' X [31:0] $end
$var wire 32 ( X_signed [31:0] $end
$var wire 32 ) Y [31:0] $end
$var wire 32 * Y_signed [31:0] $end
$var wire 1 " isEqual $end
$var reg 32 + RESULT [31:0] $end
$upscope $end
$upscope $end
$enddefinitions $end
#0
$dumpvars
bx +
bx *
bx )
bx (
bx '
bx &
bx %
bx $
bx #
x"
bx !
$end
#200
b1010 !
b1010 +
b0 %
b0 &
b101 *
1"
b101 $
b101 )
b101 (
b101 #
b101 '
#400
b110111 !
b110111 +
b1 %
b1 &
b1011 *
b1011 $
b1011 )
b1000010 (
0"
b1000010 #
b1000010 '
#600
b100 !
b100 +
b10 %
b10 &
b110 *
b110 $
b110 )
b101 (
b101 #
b101 '
#800
b111 !
b111 +
b11 %
b11 &
#1000
b100 !
b100 +
b100 %
b100 &
b10 *
b10 $
b10 )
b110 (
0"
b110 #
b110 '
#1200
b1000 !
b1000 +
b101 %
b101 &
b11 *
b11 $
b11 )
b1 (
b1 #
b1 '
#1400
b10 !
b10 +
b110 %
b110 &
b10 *
b10 $
b10 )
b1000 (
b1000 #
b1000 '
#1600
b11111111111111111111111111111110 !
b11111111111111111111111111111110 +
b111 %
b111 &
b11111111111111111111111111111000 (
b11111111111111111111111111111000 #
b11111111111111111111111111111000 '
#1800
b1 !
b1 +
b1000 %
b1000 &
b1001 *
b1001 $
b1001 )
b11111111111111111111111111111111 (
b11111111111111111111111111111111 #
b11111111111111111111111111111111 '
#2000
b0 !
b0 +
b1001 %
b1001 &
