src/RegFile.v
module RegFile(
    input [4:0]R1,
    input [4:0]R2,
    input [4:0]RD,
    input [31:0]RD_DATA,
    input WRITE_ENABLE,

    output [31:0]R1_DATA,
    output [31:0]R2_DATA
);
    reg [31:0] REGISTERS[31:0]; // 64 Bit length, 32 Registers
    
    integer i = 0;
    initial begin
        for (i = 0; i < 32 ; i = i + 1) begin
            REGISTERS[i] <= 0;
        end
    end

    assign R1_DATA = REGISTERS[R1];
    assign R2_DATA = REGISTERS[R2];

    always @(*) begin
        if (WRITE_ENABLE == 1 && RD != 0)
            REGISTERS[RD] <= RD_DATA;
    end
endmodule

testbench/tb_RegFile.v
`include "RegFile.v"
`timescale 1ns / 100ps 

module tb_RegFile;
    reg [4:0]R1;
    reg [4:0]R2;
    reg [4:0]RD;
    reg [31:0]RD_DATA;
    reg reg_write_enable;

    wire [31:0]R1_data;
    wire [31:0]R2_data;

    RegFile regfile(R1, R2, RD, RD_DATA, reg_write_enable, R1_data, R2_data );

    initial begin
        #20;

        R1 = 0;
        R2 = 0;
        RD = 0;
        RD_DATA = 0;
        reg_write_enable = 0;
        #20;

        R1 = 0;
        R2 = 0;
        RD = 1;
        RD_DATA = 5;
        reg_write_enable = 1;
        #20;

        R1 = 1;
        R2 = 0;
        RD = 2;
        RD_DATA = 10;
        reg_write_enable = 1;
        #20;

        // Test write_enable is working
        R1 = 1;
        R2 = 2;
        RD = 3;
        RD_DATA = 99;
        reg_write_enable = 0;
        #20;

        R1 = 3;
        R2 = 2;
        RD = 1;
        RD_DATA = 99;
        reg_write_enable = 0;
        #20;

        // Test R0 is write protected
        R1 = 3;
        R2 = 1;
        RD = 0;
        RD_DATA = 99;
        reg_write_enable = 1;
        #20;

        R1 = 0;
        R2 = 1;
        RD = 0;
        RD_DATA = 0;
        reg_write_enable = 0;
        #20;
    end

    initial begin
        $dumpfile("vcd/regfile.vcd");
        $dumpvars(0, tb_RegFile);
    end
endmodule

testbench/vcd/regfile.vcd
$date
	Sun Dec  4 14:45:25 2022
$end
$version
	Icarus Verilog
$end
$timescale
	100ps
$end
$scope module tb_RegFile $end
$var wire 32 ! R2_data [31:0] $end
$var wire 32 " R1_data [31:0] $end
$var reg 5 # R1 [4:0] $end
$var reg 5 $ R2 [4:0] $end
$var reg 5 % RD [4:0] $end
$var reg 32 & RD_DATA [31:0] $end
$var reg 1 ' reg_write_enable $end
$scope module regfile $end
$var wire 5 ( R1 [4:0] $end
$var wire 32 ) R1_DATA [31:0] $end
$var wire 5 * R2 [4:0] $end
$var wire 32 + R2_DATA [31:0] $end
$var wire 5 , RD [4:0] $end
$var wire 32 - RD_DATA [31:0] $end
$var wire 1 ' WRITE_ENABLE $end
$var integer 32 . i [31:0] $end
$upscope $end
$upscope $end
$enddefinitions $end
#0
$dumpvars
b100000 .
bx -
bx ,
bx +
bx *
bx )
bx (
x'
bx &
bx %
bx $
bx #
bx "
bx !
$end
#200
0'
b0 &
b0 -
b0 %
b0 ,
b0 !
b0 +
b0 $
b0 *
b0 "
b0 )
b0 #
b0 (
#400
1'
b101 &
b101 -
b1 %
b1 ,
#600
b1010 &
b1010 -
b10 %
b10 ,
b101 "
b101 )
b1 #
b1 (
#800
0'
b1100011 &
b1100011 -
b11 %
b11 ,
b1010 !
b1010 +
b10 $
b10 *
#1000
b1 %
b1 ,
b0 "
b0 )
b11 #
b11 (
#1200
1'
b0 %
b0 ,
b101 !
b101 +
b1 $
b1 *
#1400
0'
b0 &
b0 -
b0 #
b0 (
