src/ROM.v
module ROM(
    input [9:0] ADDRESS,    
    output [31:0] DATA
);
    reg [31:0] memory [0:1023]; // 10-bit address. 32-bit cell size.

    assign DATA = memory[ADDRESS];

    initial begin
        $readmemh("../example/Program.hex", memory);

        // Example program:
        /*
        memory[0] = 32'h00000013; // nop (add x0 x0 0)
        
        // start:
        memory[1] = 32'h00100093; // addi x1 x0 1
        memory[2] = 32'h00100313; // addi x6 x0 1
        memory[3] = 32'h00400613; // addi x12 x0 4
        memory[4] = 32'h00602023; // sw x6 0(x0)        x6 R2 Dep (WB)

        // loop:
        memory[5] = 32'h00002303; // lw x6 0(x0)        
        memory[6] = 32'h00130313; // addi x6 x6 1       LoadStall and x6 R1 Dep (WB)
        memory[7] = 32'h00602023; // sw x6 0(x0)        x6 R2 Dep
        memory[8] = 32'hFEC34AE3; // blt x6 x12 -12     x6 R1 Dep (WB)

        // finish:
        memory[9] = 32'h00000013; // nop (add x0 x0 0)
        */
    end
endmodule

testbench/tb_ROM.v
`include "ROM.v"
`timescale 1ns / 100ps 

module tb_ROM;
    reg [9:0] ADDRESS;
    reg [31:0] DATA_OUT;

    ROM rom(ADDRESS, DATA_OUT);

    initial begin
        #20;
        
        ADDRESS = 0; #20;
        ADDRESS = 1; #20;
        ADDRESS = 2; #20;
        ADDRESS = 3; #20;
        ADDRESS = 4; #20;
        ADDRESS = 5; #20;
        ADDRESS = 6; #20;
        ADDRESS = 7; #20;
        ADDRESS = 8; #20;
        ADDRESS = 9; #20;
        ADDRESS = 10; #20;
        ADDRESS = 11; #20;
        ADDRESS = 20; #20;
    end

    initial begin
        $dumpfile("vcd/rom.vcd");
        $dumpvars(0, tb_ROM);
    end
endmodule

testbench/vcd/rom.vcd
$date
	Sun Dec  4 14:45:25 2022
$end
$version
	Icarus Verilog
$end
$timescale
	100ps
$end
$scope module tb_ROM $end
$var wire 32 ! DATA_OUT [31:0] $end
$var reg 10 " ADDRESS [9:0] $end
$scope module rom $end
$var wire 10 # ADDRESS [9:0] $end
$var wire 32 $ DATA [31:0] $end
$upscope $end
$upscope $end
$enddefinitions $end
#0
$dumpvars
bx $
bx #
bx "
bx !
$end
#200
b10011 !
b10011 $
b0 "
b0 #
#400
b100000000000010010011 !
b100000000000010010011 $
b1 "
b1 #
#600
b100000000001100010011 !
b100000000001100010011 $
b10 "
b10 #
#800
b10000000000011000010011 !
b10000000000011000010011 $
b11 "
b11 #
#1000
b11000000010000000100011 !
b11000000010000000100011 $
b100 "
b100 #
#1200
b10001100000011 !
b10001100000011 $
b101 "
b101 #
#1400
b100110000001100010011 !
b100110000001100010011 $
b110 "
b110 #
#1600
b11000000010000000100011 !
b11000000010000000100011 $
b111 "
b111 #
#1800
b11111110110000110100101011100011 !
b11111110110000110100101011100011 $
b1000 "
b1000 #
#2000
b10011 !
b10011 $
b1001 "
b1001 #
#2200
bx !
bx $
b1010 "
b1010 #
#2400
b1011 "
b1011 #
#2600
b10100 "
b10100 #
